{
  "coord": {
    "lon": 55.3047,
    "lat": 25.2582
  },
  "weather": [
    {
      "id": 800,
      "main": "Clear",
      "description": "clear sky",
      "icon": "01d"
    }
  ],
  "base": "stations",
  "main": {
    "temp": 35.08,
    "feels_like": 41.27,
    "temp_min": 35.08,
    "temp_max": 35.08,
    "pressure": 1001,
    "humidity": 51,
    "sea_level": 1001,
    "grnd_level": 1000
  },
  "visibility": 10000,
  "wind": {
    "speed": 4.89,
    "deg": 283,
    "gust": 7.9
  },
  "clouds": {
    "all": 0
  },
  "dt": 1781172736,
  "sys": {
    "country": "AE",
    "sunrise": 1781141281,
    "sunset": 1781190535
  },
  "timezone": 14400,
  "id": 292223,
  "name": "Dubai",
  "cod": 200
}